odoo/addons/stock_orderpoint_origin/README.rst
odoo/addons/stock_orderpoint_origin/__init__.py
odoo/addons/stock_orderpoint_origin/__manifest__.py
odoo/addons/stock_orderpoint_origin/i18n/it.po
odoo/addons/stock_orderpoint_origin/i18n/stock_orderpoint_origin.pot
odoo/addons/stock_orderpoint_origin/models/__init__.py
odoo/addons/stock_orderpoint_origin/models/procurement_group.py
odoo/addons/stock_orderpoint_origin/models/purchase_order.py
odoo/addons/stock_orderpoint_origin/readme/CONTRIBUTORS.rst
odoo/addons/stock_orderpoint_origin/readme/DESCRIPTION.rst
odoo/addons/stock_orderpoint_origin/readme/USAGE.rst
odoo/addons/stock_orderpoint_origin/static/description/icon.png
odoo/addons/stock_orderpoint_origin/static/description/index.html
odoo/addons/stock_orderpoint_origin/tests/__init__.py
odoo/addons/stock_orderpoint_origin/tests/test_stock_orderpoint.py
odoo_addon_stock_orderpoint_origin-16.0.1.0.0.5.dist-info/METADATA
odoo_addon_stock_orderpoint_origin-16.0.1.0.0.5.dist-info/WHEEL
odoo_addon_stock_orderpoint_origin-16.0.1.0.0.5.dist-info/top_level.txt
odoo_addon_stock_orderpoint_origin-16.0.1.0.0.5.dist-info/RECORD
